<?xml version="1.0"?>
<opencv_storage>
<stage0>
  <maxWeakCount>3</maxWeakCount>
  <stageThreshold>2.2969438135623932e-01</stageThreshold>
  <weakClassifiers>
    <_>
      <internalNodes>
        0 -1 82736 -1.5439429879188538e-01</internalNodes>
      <leafValues>
        7.0370370149612427e-01 -9.3939393758773804e-01</leafValues></_>
    <_>
      <internalNodes>
        0 -1 153462 -1.0731213260442019e-03</internalNodes>
      <leafValues>
        5.6179428100585938e-01 -8.6808115243911743e-01</leafValues></_>
    <_>
      <internalNodes>
        0 -1 25291 -4.9924460472539067e-04</internalNodes>
      <leafValues>
        6.0729402303695679e-01 -8.5380923748016357e-01</leafValues></_></weakClassifiers></stage0>
</opencv_storage>
